MANIFEST.in
README.md
setup.py
mezzanineHtmlSlides.egg-info/PKG-INFO
mezzanineHtmlSlides.egg-info/SOURCES.txt
mezzanineHtmlSlides.egg-info/dependency_links.txt
mezzanineHtmlSlides.egg-info/not-zip-safe
mezzanineHtmlSlides.egg-info/requires.txt
mezzanineHtmlSlides.egg-info/top_level.txt
mezzaninehtmlslides/__init__.py
mezzaninehtmlslides/admin.py
mezzaninehtmlslides/models.py
mezzaninehtmlslides/static/css/responsiveslides.css
mezzaninehtmlslides/static/js/responsiveslides.min.js
mezzaninehtmlslides/templates/base.html
mezzaninehtmlslides/templates/pages/page.html