Metadata-Version: 1.1
Name: mezzanineHtmlSlides
Version: 0.1.1
Summary: Plug a html slideshow into your mezzanine website on all pages.
Home-page: http://github.com/tjankov/mezzanineHtmlSlides
Author: Tonino Jankov
Author-email: tyaakow@gmail.com
License: Simplified BSD
Download-URL: http://github.com/tjankov/mezzanineHtmlSlides/downloads
Platform: UNKNOWN
Classifier: Environment :: Web Environment
Classifier: Intended Audience :: Developers
Classifier: License :: OSI Approved :: BSD License
Classifier: Operating System :: OS Independent
Classifier: Programming Language :: Python
Classifier: Framework :: Django
